oapapersviewer/__init__.py
oapapersviewer/__main__.py
oapapersviewer/bindings_dock_view.py
oapapersviewer/document_tree.py
oapapersviewer/footer.py
oapapersviewer/inputs.py
oapapersviewer/json_tree.py
oapapersviewer/listing.py
oapapersviewer/sample_view.py
oapapersviewer/viewer.py
oapapersviewer-1.0.0.dist-info/METADATA
oapapersviewer-1.0.0.dist-info/WHEEL
oapapersviewer-1.0.0.dist-info/entry_points.txt
oapapersviewer-1.0.0.dist-info/RECORD
