Metadata-Version: 2.3
Name: oapapersviewer
Version: 1.0.0
Dynamic: Requires-Dist
Summary: TUI viewer for OAPapers corpus and derived datasets.
Project-URL: Repository, https://github.com/KNOT-FIT-BUT/OAPapersViewer
Author: Martin Dočekal
Keywords: OAPapers,OARelatedWork,TUI,viewer
Requires-Python: >=3.10
